README.md
UndoPy.py
setup.py
undopy.egg-info/PKG-INFO
undopy.egg-info/SOURCES.txt
undopy.egg-info/dependency_links.txt
undopy.egg-info/top_level.txt